README.txt
setup.py
convert2txt.egg-info/PKG-INFO
convert2txt.egg-info/SOURCES.txt
convert2txt.egg-info/dependency_links.txt
convert2txt.egg-info/top_level.txt
html2txt/__init__.py
html2txt/convert2txt.py
html2txt/html_to_txt.py